gmpacket/README.md
gmpacket/__init__.py
gmpacket/feature.py
gmpacket/packet.py
gmpacket/provenance.py
gmpacket/scan.py
gmpacket/utils.py
gmpacket/validate.py
gmpacket/data/examples/borehole_example.json
gmpacket/data/examples/example1.json
gmpacket/data/examples/multichannel_example.json
gmpacket/data/examples/sps-100-200-example.json
gmpacket-0.1.8.dist-info/licenses/LICENSE.md
gmpacket-0.1.8.dist-info/METADATA
gmpacket-0.1.8.dist-info/WHEEL
gmpacket-0.1.8.dist-info/top_level.txt
gmpacket-0.1.8.dist-info/RECORD
