Metadata-Version: 2.4
Name: gmpacket
Version: 0.1.8
Summary: ANSS Ground Motion Packet
Author-email: Mike Hearne <mhearne@usgs.gov>, Eric Thompson <ethompson@usgs.gov>, Ellen Yu <eyu@caltech.edu>, Lijam Hagos <lijam.hagos@conservation.ca.gov>, Jamie Steidl <steidl@ucsb.edu>, Bruce Worden <cbworden@contractor.usgs.gov>
License: License
Keywords: ground motion,earthquake
Requires-Python: >=3.8
License-File: LICENSE.md
Requires-Dist: geopy>=2.1.0
Requires-Dist: pandas>=1.4.0
Requires-Dist: pydantic[email]>=2.0
Requires-Dist: setuptools-scm>=6.3.2
Provides-Extra: dev
Requires-Dist: black>=21; extra == "dev"
Requires-Dist: flake8>=3.9; extra == "dev"
Requires-Dist: ipython>=7.26; extra == "dev"
Requires-Dist: setuptools_scm; extra == "dev"
Requires-Dist: notebook>=6.4.1; extra == "dev"
Provides-Extra: test
Requires-Dist: deepdiff>=5.7.0; extra == "test"
Requires-Dist: openpyxl>=3.0.9; extra == "test"
Requires-Dist: pytest>=6.2; extra == "test"
Requires-Dist: pytest-cov>=2.12.0; extra == "test"
Provides-Extra: doc
Requires-Dist: sphinx>5.0.0; extra == "doc"
Requires-Dist: requests>=2.28.2; extra == "doc"
Requires-Dist: furo>=2023.3.27; extra == "doc"
Requires-Dist: myst-nb>=0.17.2; extra == "doc"
Requires-Dist: myst-parser>=0.18.1; extra == "doc"
Requires-Dist: altair>=4.2.2; extra == "doc"
Requires-Dist: nbsphinx>=0.9.1; extra == "doc"
Requires-Dist: recommonmark>=0.7.1; extra == "doc"
Requires-Dist: sphinx-autoapi>=2.1.0; extra == "doc"
Requires-Dist: sphinx-copybutton>=0.5.2; extra == "doc"
Requires-Dist: sphinx-inline-tabs>=2023.4.21; extra == "doc"
Requires-Dist: sphinxcontrib-programoutput>=0.17; extra == "doc"
Provides-Extra: build
Requires-Dist: build; extra == "build"
Requires-Dist: twine; extra == "build"
Dynamic: license-file
